noattr/__init__.py
noattr-0.0.9.dist-info/DESCRIPTION.rst
noattr-0.0.9.dist-info/METADATA
noattr-0.0.9.dist-info/RECORD
noattr-0.0.9.dist-info/WHEEL
noattr-0.0.9.dist-info/eager_resources.txt
noattr-0.0.9.dist-info/metadata.json
noattr-0.0.9.dist-info/top_level.txt
