Metadata-Version: 1.1
Name: noattr
Version: 0.0.9
Summary: To avoid NoneType AttributeError exception on chained attributes
Home-page: https://github.com/elapouya/noattr
Author: Eric Lapouyade
Author-email: elapouya@gmail.com
License: LGPL 2.1
Keywords: attribute,AttrDict
Platform: UNKNOWN
Classifier: Intended Audience :: Developers
Classifier: Development Status :: 4 - Beta
Classifier: Programming Language :: Python :: 2
Classifier: Programming Language :: Python :: 3
